odoo/addons/purchase_tag/README.rst
odoo/addons/purchase_tag/__init__.py
odoo/addons/purchase_tag/__manifest__.py
odoo/addons/purchase_tag/i18n/es.po
odoo/addons/purchase_tag/i18n/it.po
odoo/addons/purchase_tag/i18n/pt_BR.po
odoo/addons/purchase_tag/i18n/purchase_tag.pot
odoo/addons/purchase_tag/models/__init__.py
odoo/addons/purchase_tag/models/purchase_order.py
odoo/addons/purchase_tag/models/purchase_tag.py
odoo/addons/purchase_tag/readme/CONTRIBUTORS.md
odoo/addons/purchase_tag/readme/DESCRIPTION.md
odoo/addons/purchase_tag/readme/USAGE.md
odoo/addons/purchase_tag/security/ir.model.access.csv
odoo/addons/purchase_tag/static/description/icon.png
odoo/addons/purchase_tag/static/description/index.html
odoo/addons/purchase_tag/tests/__init__.py
odoo/addons/purchase_tag/tests/test_purchase_tag.py
odoo/addons/purchase_tag/views/purchase_tag_view.xml
odoo/addons/purchase_tag/views/purchase_view.xml
odoo_addon_purchase_tag-18.0.1.1.0.2.dist-info/METADATA
odoo_addon_purchase_tag-18.0.1.1.0.2.dist-info/WHEEL
odoo_addon_purchase_tag-18.0.1.1.0.2.dist-info/top_level.txt
odoo_addon_purchase_tag-18.0.1.1.0.2.dist-info/RECORD
